braintest/__init__.py
braintest/__main__.py
braintest-0.0.1.dist-info/METADATA
braintest-0.0.1.dist-info/WHEEL
braintest-0.0.1.dist-info/entry_points.txt
braintest-0.0.1.dist-info/licenses/LICENSE
braintest-0.0.1.dist-info/RECORD
