Metadata-Version: 2.3
Name: braintest
Version: 0.0.1
Summary: Write brainf*ck programs with your unit tests.
Project-URL: Homepage, https://github.com/etopiei/braintest
Project-URL: Issues, https://github.com/etopiei/braintest/issues
Author-email: etopiei <me.etopiei@gmail.com>
License-File: LICENSE
Classifier: License :: OSI Approved :: MIT License
Classifier: Operating System :: OS Independent
Classifier: Programming Language :: Python :: 3
Requires-Python: >=3.8
